pi_json/__init__.py
pi_json/pi_json.py
test/__init__.py
test/clz.py
test/run_test.py
pipi_json-1.0.1.dist-info/METADATA
pipi_json-1.0.1.dist-info/WHEEL
pipi_json-1.0.1.dist-info/top_level.txt
pipi_json-1.0.1.dist-info/RECORD
