Metadata-Version: 2.1
Name: pipi-json
Version: 1.0.1
Summary: JSON supported
Home-page: https://github.com/eronrunner/pipi_json
Author: Eron
Author-email: eron.runner@gmail.com
License: MIT
Platform: UNKNOWN
Classifier: License :: OSI Approved :: MIT License
Classifier: Programming Language :: Python :: 3
Classifier: Programming Language :: Python :: 3.7
